squid_game_doll/__init__.py
squid_game_doll/__main__.py
squid_game_doll/async_screen_saver.py
squid_game_doll/base_player_tracker.py
squid_game_doll/calibrator.py
squid_game_doll/config_phase.py
squid_game_doll/constants.py
squid_game_doll/cuda_utils.py
squid_game_doll/display.py
squid_game_doll/face_extractor.py
squid_game_doll/game_camera.py
squid_game_doll/game_screen.py
squid_game_doll/game_settings.py
squid_game_doll/img_processing.py
squid_game_doll/laser_coordinate_filter.py
squid_game_doll/laser_finder.py
squid_game_doll/laser_finder_nn.py
squid_game_doll/laser_shooter.py
squid_game_doll/laser_tracker.py
squid_game_doll/media/SpaceGrotesk-Bold.ttf
squid_game_doll/media/SpaceGrotesk-Regular.ttf
squid_game_doll/media/background-2.png
squid_game_doll/media/background.jpg
squid_game_doll/media/eliminated.mp3
squid_game_doll/media/flute.mp3
squid_game_doll/media/font_lcd.ttf
squid_game_doll/media/green_light.mp3
squid_game_doll/media/gunshot.mp3
squid_game_doll/media/init.mp3
squid_game_doll/media/intro.mp3
squid_game_doll/media/loading_screen.webp
squid_game_doll/media/logo.png
squid_game_doll/media/mingle.mp3
squid_game_doll/media/pig.png
squid_game_doll/media/red_light.mp3
squid_game_doll/media/sample_player.jpg
squid_game_doll/media/shooter.png
squid_game_doll/media/shooter_off.png
squid_game_doll/media/success.mp3
squid_game_doll/player.py
squid_game_doll/player_tracker_hailo.py
squid_game_doll/player_tracker_ul.py
squid_game_doll/run.py
squid_game_doll/squid_game.py
squid_game_doll/utils/__init__.py
squid_game_doll/utils/platform.py
squid_game_doll/utils.py
squid_game_doll/victory_animation.py
squid_game_doll-0.3.0.dist-info/LICENSE
squid_game_doll-0.3.0.dist-info/METADATA
squid_game_doll-0.3.0.dist-info/WHEEL
squid_game_doll-0.3.0.dist-info/entry_points.txt
squid_game_doll-0.3.0.dist-info/RECORD
