Metadata-Version: 2.3
Name: squid-game-doll
Version: 0.3.0
Summary: A game using AI for player tracking inspired by Squid Game TV series, featuring an animated doll with laser.
License: MIT
Keywords: squid game,doll,laser,camera,tracking,control,robotics,computer vision
Author: Pascal Brunot
Author-email: pascal.brunot@fablabbergamo.it
Requires-Python: >=3.9
Classifier: License :: OSI Approved :: MIT License
Classifier: Programming Language :: Python :: 3
Classifier: Programming Language :: Python :: 3.9
Classifier: Programming Language :: Python :: 3.10
Classifier: Programming Language :: Python :: 3.11
Classifier: Programming Language :: Python :: 3.12
Classifier: Programming Language :: Python :: 3.13
Provides-Extra: cuda
Provides-Extra: hailo
Provides-Extra: jetson
Provides-Extra: standard
Requires-Dist: Camera (==1.3.0)
Requires-Dist: Pillow (==11.1.0)
Requires-Dist: cv2_enumerate_cameras (==1.1.18.2)
Requires-Dist: imutils (==0.5.4)
Requires-Dist: lap (>=0.5.12)
Requires-Dist: lmfit (==1.3.2)
Requires-Dist: loguru (==0.7.2)
Requires-Dist: matplotlib
Requires-Dist: mediapipe
Requires-Dist: mediapipe (==0.10.18)
Requires-Dist: numpy (<2)
Requires-Dist: pandas (==2.2.3)
Requires-Dist: perlin-numpy (==0.0.1)
Requires-Dist: psutil
Requires-Dist: pygame (==2.6.1)
Requires-Dist: requests (>=2.32.2)
Requires-Dist: scikit-image
Requires-Dist: scikit-learn (==1.6.1)
Requires-Dist: scipy
Requires-Dist: seaborn
Requires-Dist: setuptools (>=70.0.0)
Requires-Dist: simple-pid (==2.0.1)
Requires-Dist: supervision
Requires-Dist: torch ; extra == "standard"
Requires-Dist: torchvision ; extra == "standard"
Requires-Dist: ultralytics ; extra == "standard"
